gpjax/__init__.py
gpjax/citation.py
gpjax/dataset.py
gpjax/distributions.py
gpjax/fit.py
gpjax/gps.py
gpjax/integrators.py
gpjax/likelihoods.py
gpjax/mean_functions.py
gpjax/numpyro_extras.py
gpjax/objectives.py
gpjax/parameters.py
gpjax/scan.py
gpjax/typing.py
gpjax/variational_families.py
gpjax/kernels/__init__.py
gpjax/kernels/base.py
gpjax/kernels/approximations/__init__.py
gpjax/kernels/approximations/rff.py
gpjax/kernels/computations/__init__.py
gpjax/kernels/computations/base.py
gpjax/kernels/computations/basis_functions.py
gpjax/kernels/computations/constant_diagonal.py
gpjax/kernels/computations/dense.py
gpjax/kernels/computations/diagonal.py
gpjax/kernels/computations/eigen.py
gpjax/kernels/non_euclidean/__init__.py
gpjax/kernels/non_euclidean/graph.py
gpjax/kernels/non_euclidean/utils.py
gpjax/kernels/nonstationary/__init__.py
gpjax/kernels/nonstationary/arccosine.py
gpjax/kernels/nonstationary/linear.py
gpjax/kernels/nonstationary/polynomial.py
gpjax/kernels/stationary/__init__.py
gpjax/kernels/stationary/base.py
gpjax/kernels/stationary/matern12.py
gpjax/kernels/stationary/matern32.py
gpjax/kernels/stationary/matern52.py
gpjax/kernels/stationary/periodic.py
gpjax/kernels/stationary/powered_exponential.py
gpjax/kernels/stationary/rational_quadratic.py
gpjax/kernels/stationary/rbf.py
gpjax/kernels/stationary/utils.py
gpjax/kernels/stationary/white.py
gpjax/linalg/__init__.py
gpjax/linalg/operations.py
gpjax/linalg/operators.py
gpjax/linalg/utils.py
gpjax-0.13.3.dist-info/METADATA
gpjax-0.13.3.dist-info/WHEEL
gpjax-0.13.3.dist-info/licenses/LICENSE.txt
gpjax-0.13.3.dist-info/RECORD
