Metadata-Version: 2.4
Name: gpjax
Version: 0.13.3
Summary: Gaussian processes in JAX.
Project-URL: Documentation, https://docs.jaxgaussianprocesses.com/
Project-URL: Issues, https://github.com/thomaspinder/GPJax/issues
Project-URL: Source, https://github.com/thomaspinder/GPJax
Author-email: Thomas Pinder <tompinder@live.co.uk>
License: MIT
License-File: LICENSE.txt
Keywords: gaussian-processes jax machine-learning bayesian
Classifier: Development Status :: 4 - Beta
Classifier: Programming Language :: Python
Classifier: Programming Language :: Python :: 3.11
Classifier: Programming Language :: Python :: 3.12
Classifier: Programming Language :: Python :: 3.13
Classifier: Programming Language :: Python :: Implementation :: CPython
Classifier: Programming Language :: Python :: Implementation :: PyPy
Requires-Python: >=3.11
Requires-Dist: beartype>0.16.1
Requires-Dist: flax>=0.12.0
Requires-Dist: jax>=0.5.0
Requires-Dist: jaxlib>=0.5.0
Requires-Dist: jaxtyping>0.2.10
Requires-Dist: numpy>=2.0.0
Requires-Dist: numpyro
Requires-Dist: optax>0.2.1
Requires-Dist: tqdm>4.66.2
Provides-Extra: dev
Requires-Dist: absolufy-imports>=0.3.1; extra == 'dev'
Requires-Dist: autoflake; extra == 'dev'
Requires-Dist: black; extra == 'dev'
Requires-Dist: codespell>=2.2.4; extra == 'dev'
Requires-Dist: coverage>=7.2.2; extra == 'dev'
Requires-Dist: interrogate>=1.5.0; extra == 'dev'
Requires-Dist: isort; extra == 'dev'
Requires-Dist: jupytext; extra == 'dev'
Requires-Dist: mktestdocs>=0.2.1; extra == 'dev'
Requires-Dist: networkx; extra == 'dev'
Requires-Dist: pre-commit>=3.2.2; extra == 'dev'
Requires-Dist: pytest-beartype; extra == 'dev'
Requires-Dist: pytest-cov>=4.0.0; extra == 'dev'
Requires-Dist: pytest-pretty>=1.1.1; extra == 'dev'
Requires-Dist: pytest-xdist>=3.2.1; extra == 'dev'
Requires-Dist: pytest>=7.2.2; extra == 'dev'
Requires-Dist: ruff>=0.6; extra == 'dev'
Requires-Dist: xdoctest>=1.1.1; extra == 'dev'
Provides-Extra: docs
Requires-Dist: blackjax>=0.9.6; extra == 'docs'
Requires-Dist: ipykernel>=6.22.0; extra == 'docs'
Requires-Dist: ipython>=8.11.0; extra == 'docs'
Requires-Dist: ipywidgets>=8.0.5; extra == 'docs'
Requires-Dist: jupytext>=1.14.5; extra == 'docs'
Requires-Dist: markdown-katex>=202406.1035; extra == 'docs'
Requires-Dist: matplotlib>=3.7.1; extra == 'docs'
Requires-Dist: mkdocs-gen-files>=0.5.0; extra == 'docs'
Requires-Dist: mkdocs-git-authors-plugin>=0.7.0; extra == 'docs'
Requires-Dist: mkdocs-jupyter>=0.24.3; extra == 'docs'
Requires-Dist: mkdocs-literate-nav>=0.6.0; extra == 'docs'
Requires-Dist: mkdocs-material>=9.5.12; extra == 'docs'
Requires-Dist: mkdocs>=1.5.3; extra == 'docs'
Requires-Dist: mkdocstrings[python]<0.31.0; extra == 'docs'
Requires-Dist: nbconvert>=7.16.2; extra == 'docs'
Requires-Dist: networkx>=3.0; extra == 'docs'
Requires-Dist: pandas>=1.5.3; extra == 'docs'
Requires-Dist: pymdown-extensions>=10.7.1; extra == 'docs'
Requires-Dist: scikit-learn>=1.5.1; extra == 'docs'
Requires-Dist: seaborn>=0.12.2; extra == 'docs'
Requires-Dist: watermark>=2.3.1; extra == 'docs'
